mdbrew/__init__.py
mdbrew/__version__.py
mdbrew/analysis/__init__.py
mdbrew/analysis/atom.py
mdbrew/analysis/autocorrelation.py
mdbrew/analysis/centerofmass.py
mdbrew/analysis/hydrogenbonding.py
mdbrew/analysis/msd.py
mdbrew/analysis/rdf.py
mdbrew/application/__init__.py
mdbrew/application/cp2k.py
mdbrew/main/__init__.py
mdbrew/main/brewery.py
mdbrew/main/fmt/__init__.py
mdbrew/main/fmt/gromacs/__init__.py
mdbrew/main/fmt/gromacs/opener_gro.py
mdbrew/main/fmt/gromacs/opener_trr.py
mdbrew/main/fmt/lammps/__init__.py
mdbrew/main/fmt/lammps/opener_lammpstrj.py
mdbrew/main/fmt/lammps/writer_lmps.py
mdbrew/main/fmt/pdb/__init__.py
mdbrew/main/fmt/pdb/opener_pdb.py
mdbrew/main/fmt/vasp/__init__.py
mdbrew/main/fmt/vasp/opener_xdatcar.py
mdbrew/main/fmt/vasp/writer_poscar.py
mdbrew/main/fmt/xyz/__init__.py
mdbrew/main/fmt/xyz/opener_extxyz.py
mdbrew/main/fmt/xyz/opener_xyz.py
mdbrew/main/fmt/xyz/writer_xyz.py
mdbrew/main/interface/__init__.py
mdbrew/main/interface/opener.py
mdbrew/main/interface/writer.py
mdbrew/tool/__init__.py
mdbrew/tool/colorfont.py
mdbrew/tool/decorator.py
mdbrew/tool/path.py
mdbrew/tool/plot.py
mdbrew/tool/space/__init__.py
mdbrew/tool/space/_periodic_kdtree.py
mdbrew/tool/space/_spacer.py
mdbrew-2.5.7.dist-info/LICENSE.md
mdbrew-2.5.7.dist-info/METADATA
mdbrew-2.5.7.dist-info/WHEEL
mdbrew-2.5.7.dist-info/top_level.txt
mdbrew-2.5.7.dist-info/RECORD
