Metadata-Version: 2.1
Name: mdbrew
Version: 2.5.7
Summary: Postprocessing tools for the Molecular Dynamics simulation
Home-page: https://github.com/minu928/mdbrew
Author: Knu
Author-email: minu928@snu.ac.kr
Keywords: MD,LAMMPS,GROMACS
Requires-Python: >=3.8
License-File: LICENSE.md
